Metadata-Version: 2.1
Name: numpysane
Version: 0.39
Summary: more-reasonable core functionality for numpy
Home-page: http://github.com/dkogan/numpysane
Author: Dima Kogan
Author-email: dima@secretsauce.net
License: LGPL
License-File: LICENSE
